stativ/__init__.py
stativ/__main__.py
stativ/backup_store.py
stativ/cli.py
stativ/delta_store.py
stativ/prefix_store.py
stativ/stativ.py
stativ-2023.10.21.dist-info/LICENSE
stativ-2023.10.21.dist-info/METADATA
stativ-2023.10.21.dist-info/WHEEL
stativ-2023.10.21.dist-info/entry_points.txt
stativ-2023.10.21.dist-info/top_level.txt
stativ-2023.10.21.dist-info/RECORD
